rest_health/__init__.py
rest_health/adapters/__init__.py
rest_health/adapters/fastapi.py
rest_health/adapters/flask.py
rest_health/core/__init__.py
rest_health/core/checker.py
rest_health-0.1.1.dist-info/licenses/LICENSE
rest_health-0.1.1.dist-info/METADATA
rest_health-0.1.1.dist-info/WHEEL
rest_health-0.1.1.dist-info/top_level.txt
rest_health-0.1.1.dist-info/RECORD
