Metadata-Version: 2.4
Name: rest-health
Version: 0.1.1
Summary: Framework-agnostic REST healthcheck endpoints for Python web apps
Author-email: Fabricio Entringer <fabricio.entringer@example.com>
License: MIT License
Project-URL: Homepage, https://github.com/fabricio-entringer/rest-health
Project-URL: Repository, https://github.com/fabricio-entringer/rest-health
Project-URL: Issues, https://github.com/fabricio-entringer/rest-health/issues
Keywords: health,healthcheck,rest,api,fastapi,flask
Classifier: Development Status :: 4 - Beta
Classifier: Intended Audience :: Developers
Classifier: License :: OSI Approved :: MIT License
Classifier: Operating System :: OS Independent
Classifier: Programming Language :: Python :: 3
Classifier: Programming Language :: Python :: 3.8
Classifier: Programming Language :: Python :: 3.9
Classifier: Programming Language :: Python :: 3.10
Classifier: Programming Language :: Python :: 3.11
Classifier: Programming Language :: Python :: 3.12
Classifier: Topic :: Internet :: WWW/HTTP
Classifier: Topic :: Software Development :: Libraries :: Python Modules
Classifier: Topic :: System :: Monitoring
Requires-Python: >=3.8
License-File: LICENSE
Provides-Extra: fastapi
Requires-Dist: fastapi; extra == "fastapi"
Provides-Extra: flask
Requires-Dist: flask; extra == "flask"
Provides-Extra: dev
Requires-Dist: pytest>=6.0; extra == "dev"
Requires-Dist: pytest-cov; extra == "dev"
Requires-Dist: black; extra == "dev"
Requires-Dist: flake8; extra == "dev"
Requires-Dist: mypy; extra == "dev"
Requires-Dist: build>=0.10; extra == "dev"
Requires-Dist: fastapi; extra == "dev"
Requires-Dist: pydantic; extra == "dev"
Requires-Dist: flask; extra == "dev"
Dynamic: license-file
